{
    "configurations": [
        {
            "name": "Linux",
            "includePath": [
                "${default}",
                "imgui_modified",
                "imgui_modified/filedialog_modified",
                "imgui_modified/stb_image",
                "/usr/include/SDL2"
            ],
            "defines": [],
            "compilerPath": "/usr/bin/gcc",
            "cStandard": "c17",
            "cppStandard": "c++17",
            "configurationProvider": "ms-vscode.makefile-tools"
        }
    ],
    "version": 4
}